{
    "iid": "201802224",
    "source": [
        {
            "name": "百域阁(全网)",
            "url": "http://api.baiyug.cn/vip/index.php",
            "Referer":"http://api.baiyug.cn",
            "parseName":"baiyug"
        },
        {
            "name": "石头解析(全网)",
            "url": "http://014670.cn/2018/222.php",
            "Referer":"http://014670.cn",
            "parseName":"shitou"
        },
        {
            "name": "那片解析(全网)",
            "url": "http://api.nepian.com/ckparse/",
            "Referer":"http://api.nepian.com",
            "parseName":"napian"
        }
    ]
}
//http://014670.cn/2018/222.php
//http://014670.cn/jx/mg.php
